{
  "timestamp": "20260428_0446",
  "nlp_method": "tfidf_regex_trade_gate_v6.1",
  "sklearn_available": true,
  "weather_cell_resolution": 0.01,
  "open_meteo_endpoint": "https://api.open-meteo.com/v1/forecast",
  "imerg_fallback_enabled": true,
  "hazard_flood_status": "OK",
  "hazard_cyclone_status": "OK (none near PK)",
  "hazard_strike_status": "OK (no events)",
  "hazard_accident_status": "OK (no events)",
  "total_nodes": 12570,
  "total_edges": 14122,
  "triggered_nodes": 0,
  "triggered_edges": 0,
  "critical_nodes": 0,
  "high_nodes": 0,
  "flood_triggered_nodes": 0,
  "cyclone_triggered_nodes": 0,
  "strike_triggered_nodes": 0,
  "accident_triggered_nodes": 0,
  "max_composite_hazard": 0.1471,
  "avg_composite_hazard": 0.0512,
  "top_risk_asset": "Junction_1767"
}